bleparser/__init__.py
bleparser/acconeer.py
bleparser/airmentor.py
bleparser/almendo.py
bleparser/altbeacon.py
bleparser/amazfit.py
bleparser/atc.py
bleparser/bluemaestro.py
bleparser/bparasite.py
bleparser/brifit.py
bleparser/bthome.py
bleparser/bthome_const.py
bleparser/const.py
bleparser/govee.py
bleparser/helpers.py
bleparser/hhcc.py
bleparser/ibeacon.py
bleparser/inkbird.py
bleparser/inode.py
bleparser/jaalee.py
bleparser/jinou.py
bleparser/kegtron.py
bleparser/kkm.py
bleparser/laica.py
bleparser/mikrotik.py
bleparser/miscale.py
bleparser/moat.py
bleparser/oral_b.py
bleparser/qingping.py
bleparser/relsib.py
bleparser/ruuvitag.py
bleparser/sensirion.py
bleparser/sensorpush.py
bleparser/smartdry.py
bleparser/switchbot.py
bleparser/teltonika.py
bleparser/thermoplus.py
bleparser/thermopro.py
bleparser/tilt.py
bleparser/xiaogui.py
bleparser/xiaomi.py
bleparser-3.7.1.dist-info/LICENSE
bleparser-3.7.1.dist-info/METADATA
bleparser-3.7.1.dist-info/WHEEL
bleparser-3.7.1.dist-info/top_level.txt
bleparser-3.7.1.dist-info/RECORD
