Metadata-Version: 2.1
Name: bleparser
Version: 3.7.1
Summary: Parser for passive BLE advertisements
Home-page: https://github.com/Ernst79/bleparser
Author: Ernst79
Author-email: e.klamer@gmail.com
Project-URL: Bug Tracker, https://github.com/Ernst79/bleparser/issues
Classifier: Programming Language :: Python :: 3
Classifier: License :: OSI Approved :: MIT License
Classifier: Operating System :: OS Independent
Requires-Python: >=3.8
License-File: LICENSE
Requires-Dist: pycryptodomex
